dscore/__init__.py
dscore/cli.py
dscore/dscore.py
dscore/servers/__init__.py
dscore/servers/cspritz.py
dscore/servers/disembl.py
dscore/servers/disopred.py
dscore/servers/disprot.py
dscore/servers/espritz.py
dscore/servers/foldindex.py
dscore/servers/globplot.py
dscore/servers/iupred.py
dscore/servers/jpred.py
dscore/servers/metapredict.py
dscore/servers/pondr.py
dscore/servers/prdos.py
dscore/servers/seg.py
dscore/utils/__init__.py
dscore/utils/formatting.py
dscore/utils/io.py
dscore/utils/parsing.py
dscore/utils/plotting.py
dscore/utils/submission.py
dscore-0.4.5.dist-info/LICENSE
dscore-0.4.5.dist-info/METADATA
dscore-0.4.5.dist-info/WHEEL
dscore-0.4.5.dist-info/entry_points.txt
dscore-0.4.5.dist-info/top_level.txt
dscore-0.4.5.dist-info/RECORD
