Metadata-Version: 2.1
Name: dscore
Version: 0.4.5
Summary: Python tool for automated, multiserver query for disordered regions in protein sequences.
Home-page: https://github.com/brisvag/dscore/
Author: Lorenzo Gaifas
Author-email: brisvag@gmail.com
License: GPL3+
Classifier: Intended Audience :: Science/Research
Classifier: License :: OSI Approved :: BSD License
Classifier: Programming Language :: Python
Requires-Python: >=3.8
License-File: LICENSE
Requires-Dist: click
Requires-Dist: jpredapi
Requires-Dist: numpy
Requires-Dist: pandas
Requires-Dist: selenium (>=4.0)
Requires-Dist: tabulate
Requires-Dist: python-slugify
Requires-Dist: matplotlib
Requires-Dist: rich
